pytorch_trainer/__init__.py
pytorch_trainer/trainer.py
pytorch_trainer/metric/__init__.py
pytorch_trainer/metric/metric.py
pytorch_trainer_tensorboard-0.1.dist-info/LICENSE
pytorch_trainer_tensorboard-0.1.dist-info/METADATA
pytorch_trainer_tensorboard-0.1.dist-info/WHEEL
pytorch_trainer_tensorboard-0.1.dist-info/top_level.txt
pytorch_trainer_tensorboard-0.1.dist-info/RECORD
