Metadata-Version: 2.1
Name: pytorch-trainer-tensorboard
Version: 0.1
Summary: A simple trainer class for pytorch with tensorboard support
Home-page: https://github.com/vamshichowdary/pytorch-trainer
Author: Vamshi Chowdary Madala
Author-email: vamchowdary72@gmail.com
License: MIT
Platform: UNKNOWN
Classifier: Programming Language :: Python :: 3
Classifier: License :: OSI Approved :: MIT License
Classifier: Operating System :: OS Independent
